txl_remote_contents/__init__.py
txl_remote_contents/main.py
txl_remote_contents-0.3.6.dist-info/METADATA
txl_remote_contents-0.3.6.dist-info/WHEEL
txl_remote_contents-0.3.6.dist-info/entry_points.txt
txl_remote_contents-0.3.6.dist-info/licenses/LICENSE.txt
txl_remote_contents-0.3.6.dist-info/RECORD
