Metadata-Version: 2.4
Name: txl_remote_contents
Version: 0.3.6
Summary: TXL plugin for remote contents
Project-URL: Source, https://github.com/davidbrochart/jpterm/plugins/remote_contents
Author-email: David Brochart <david.brochart@gmail.com>
License-Expression: MIT
License-File: LICENSE.txt
Classifier: Development Status :: 4 - Beta
Classifier: Programming Language :: Python
Classifier: Programming Language :: Python :: 3.10
Classifier: Programming Language :: Python :: 3.11
Classifier: Programming Language :: Python :: 3.12
Classifier: Programming Language :: Python :: 3.13
Classifier: Programming Language :: Python :: Implementation :: CPython
Classifier: Programming Language :: Python :: Implementation :: PyPy
Requires-Python: >=3.10
Requires-Dist: httpx-ws>=0.4.2
Requires-Dist: httpx>=0.23.1
Requires-Dist: jupyter-ydoc<4.0.0,>=3.0.2
Requires-Dist: pycrdt-websocket<0.16.0,>=0.15.3
Requires-Dist: pycrdt<0.11.0,>=0.10.9
Requires-Dist: txl==0.3.2
